spalla/Game.py
spalla/__init__.py
spalla-1.4.dist-info/METADATA
spalla-1.4.dist-info/WHEEL
spalla-1.4.dist-info/top_level.txt
spalla-1.4.dist-info/RECORD
